databricks/__init__.py
databricks/labs/__init__.py
databricks/labs/blueprint/__about__.py
databricks/labs/blueprint/__init__.py
databricks/labs/blueprint/__main__.py
databricks/labs/blueprint/_posixpath.py
databricks/labs/blueprint/cli.py
databricks/labs/blueprint/commands.py
databricks/labs/blueprint/entrypoint.py
databricks/labs/blueprint/installation.py
databricks/labs/blueprint/installer.py
databricks/labs/blueprint/limiter.py
databricks/labs/blueprint/logger.py
databricks/labs/blueprint/parallel.py
databricks/labs/blueprint/paths.py
databricks/labs/blueprint/py.typed
databricks/labs/blueprint/tui.py
databricks/labs/blueprint/upgrades.py
databricks/labs/blueprint/wheels.py
databricks_labs_blueprint-0.12.0.dist-info/METADATA
databricks_labs_blueprint-0.12.0.dist-info/WHEEL
databricks_labs_blueprint-0.12.0.dist-info/licenses/LICENSE
databricks_labs_blueprint-0.12.0.dist-info/licenses/NOTICE
databricks_labs_blueprint-0.12.0.dist-info/RECORD
