Metadata-Version: 2.4
Name: databricks-labs-blueprint
Version: 0.12.0
Summary: Common libraries for Databricks Labs
Project-URL: Issues, https://github.com/databrickslabs/blueprint/issues
Project-URL: Source, https://github.com/databrickslabs/blueprint
License-File: LICENSE
License-File: NOTICE
Keywords: Databricks
Classifier: Development Status :: 4 - Beta
Classifier: License :: Other/Proprietary License
Classifier: Programming Language :: Python
Classifier: Programming Language :: Python :: 3.10
Classifier: Programming Language :: Python :: 3.11
Classifier: Programming Language :: Python :: 3.12
Classifier: Programming Language :: Python :: 3.13
Classifier: Programming Language :: Python :: 3.14
Classifier: Programming Language :: Python :: Implementation :: CPython
Requires-Python: >=3.10
Requires-Dist: databricks-sdk>=0.16.0
Provides-Extra: yaml
Requires-Dist: pyyaml<7.0.0,>=6.0.0; extra == 'yaml'
